with_keepass/__init__.py
with_keepass/__main__.py
with_keepass-1.0.3.dist-info/licenses/LICENSE
with_keepass-1.0.3.dist-info/METADATA
with_keepass-1.0.3.dist-info/WHEEL
with_keepass-1.0.3.dist-info/entry_points.txt
with_keepass-1.0.3.dist-info/top_level.txt
with_keepass-1.0.3.dist-info/RECORD
