Metadata-Version: 2.4
Name: with-keepass
Version: 1.0.3
Summary: A command-line utility that allows you to run any command with environment variables automatically injected from a KeePass database.
Author-email: Emilio Reyes <soda480@gmail.com>
Project-URL: Homepage, https://github.com/soda480/with-keepass
Classifier: Programming Language :: Python :: 3
Classifier: Operating System :: OS Independent
Requires-Python: >=3.11
License-File: LICENSE
Requires-Dist: pykeepass
Provides-Extra: dev
Requires-Dist: build; extra == "dev"
Requires-Dist: flake8; extra == "dev"
Requires-Dist: radon; extra == "dev"
Requires-Dist: bandit; extra == "dev"
Requires-Dist: coverage; extra == "dev"
Requires-Dist: twine; extra == "dev"
Dynamic: license-file
